sap/__init__.py
sap/__main__.py
sap/cli.py
sap/template.html
sap/widget.py
python_sap-2.0.0.dist-info/AUTHORS.md
python_sap-2.0.0.dist-info/LICENSE
python_sap-2.0.0.dist-info/METADATA
python_sap-2.0.0.dist-info/WHEEL
python_sap-2.0.0.dist-info/entry_points.txt
python_sap-2.0.0.dist-info/top_level.txt
python_sap-2.0.0.dist-info/RECORD
