Metadata-Version: 2.1
Name: python-sap
Version: 2.0.0
Summary: Python Tree of Science package
Home-page: https://github.com/coreofscience/python-sap
Author: Juan David Alzate Cardona
Author-email: jdalzatec@unal.edu.co
License: MIT license
Keywords: python-sap
Platform: UNKNOWN
Classifier: Development Status :: 5 - Production/Stable
Classifier: Environment :: Console
Classifier: Intended Audience :: Developers
Classifier: Intended Audience :: Education
Classifier: License :: OSI Approved :: MIT License
Classifier: Natural Language :: English
Classifier: Programming Language :: Python :: 3
Classifier: Programming Language :: Python :: 3.7
Classifier: Programming Language :: Python :: 3.8
Classifier: Programming Language :: Python :: 3.9
Requires-Python: >=3.6
Requires-Dist: Click (<8,>=7.0)
Requires-Dist: python-igraph (<1,>=0.8.0)
Requires-Dist: wostools (<4,>=3.0.2)
